MANIFEST.in
README.md
requirements.txt
setup.py
onap_dcae_dcaepolicy_lib/__init__.py
onap_dcae_dcaepolicy_lib/dcae_policy.py
onap_dcae_dcaepolicy_lib/policies_output.py
onap_dcae_dcaepolicy_lib.egg-info/PKG-INFO
onap_dcae_dcaepolicy_lib.egg-info/SOURCES.txt
onap_dcae_dcaepolicy_lib.egg-info/dependency_links.txt
onap_dcae_dcaepolicy_lib.egg-info/top_level.txt
tests/__init__.py
tests/log_ctx.py
tests/mock_cloudify_ctx.py
tests/test_dcae_policy.py