Metadata-Version: 1.1
Name: onap-dcae-dcaepolicy-lib
Version: 2.3.0
Summary: lib of policy decorators to be used by cloudify plugins of dcae controller
Home-page: UNKNOWN
Author: Alex Shatov
Author-email: alexs@att.com
License: Apache 2
Keywords: onap policy dcae controller cloudify plugin
Platform: UNKNOWN
Classifier: Intended Audience :: Telecommunications Industry
Classifier: Programming Language :: Python :: 2.7
